pywebflowerlibpackage/__init__.py
pywebflowerlibpackage/constants/__init__.py
pywebflowerlibpackage/constants/web_bots_keywords.py
pywebflowerlibpackage-1.1.3.dist-info/LICENSE
pywebflowerlibpackage-1.1.3.dist-info/METADATA
pywebflowerlibpackage-1.1.3.dist-info/WHEEL
pywebflowerlibpackage-1.1.3.dist-info/top_level.txt
pywebflowerlibpackage-1.1.3.dist-info/RECORD
