Metadata-Version: 2.1
Name: pywebflowerlibpackage
Version: 1.1.3
Summary: flower's pywebflowerlibpackage
Home-page: https://github.com/asmexcaliburwoods/pywebflowerlib
Author: flower
Author-email: egphilippov@gmail.com
License: UNKNOWN
Project-URL: Bug Tracker, https://github.com/asmexcaliburwoods/pywebflowerlib/issues
Project-URL: Flower Growth Extension Site, https://github.com/asmexcaliburwoods
Project-URL: PyPi Profile, https://pypi.org/user/flower/
Platform: UNKNOWN
Classifier: Programming Language :: Python :: 3
Classifier: License :: OSI Approved :: GNU Lesser General Public License v3 or later (LGPLv3+)
Classifier: Operating System :: OS Independent
Requires-Python: >=3.6
License-File: LICENSE
